homr/__init__.py
homr/autocrop.py
homr/bar_line_detection.py
homr/bounding_boxes.py
homr/brace_dot_detection.py
homr/circle_of_fifths.py
homr/color_adjust.py
homr/constants.py
homr/debug.py
homr/download_utils.py
homr/image_utils.py
homr/main.py
homr/model.py
homr/music_xml_generator.py
homr/noise_filtering.py
homr/note_detection.py
homr/resize.py
homr/segmentation/__init__.py
homr/segmentation/config.py
homr/segmentation/inference_segnet.py
homr/simple_logging.py
homr/staff_detection.py
homr/staff_dewarping.py
homr/staff_parsing.py
homr/staff_parsing_tromr.py
homr/staff_position_save_load.py
homr/staff_regions.py
homr/title_detection.py
homr/transformer/__init__.py
homr/transformer/configs.py
homr/transformer/decoder_inference.py
homr/transformer/encoder_inference.py
homr/transformer/staff2score.py
homr/transformer/tokenizer_lift.json
homr/transformer/tokenizer_note.json
homr/transformer/tokenizer_pitch.json
homr/transformer/tokenizer_rhythm.json
homr/transformer/utils.py
homr/transformer/vocabulary.py
homr/type_definitions.py
homr-0.6.0.dist-info/LICENSE
homr-0.6.0.dist-info/METADATA
homr-0.6.0.dist-info/WHEEL
homr-0.6.0.dist-info/entry_points.txt
homr-0.6.0.dist-info/RECORD
