Metadata-Version: 2.1
Name: homr
Version: 0.6.0
Summary: End-to-end Optical Music Recognition (OMR) system build on top of vision transformers.
Home-page: https://github.com/liebharc/homr
License: AGPL-3.0
Author: Christian Liebhardt
Author-email: christian.liebhardt@arcor.de
Requires-Python: >=3.10,<3.13
Classifier: License :: OSI Approved :: GNU Affero General Public License v3
Classifier: Programming Language :: Python :: 3
Classifier: Programming Language :: Python :: 3.10
Classifier: Programming Language :: Python :: 3.11
Classifier: Programming Language :: Python :: 3.12
Requires-Dist: Pillow (>=11.3.0,<12.0.0)
Requires-Dist: musicxml (==1.4)
Requires-Dist: numpy (>=2.2.6,<3.0.0)
Requires-Dist: onnxruntime (>=1.22.1,<2.0.0)
Requires-Dist: opencv-python-headless (>=4.12.0.88,<5.0.0.0)
Requires-Dist: rapidocr-onnxruntime (>=1.4.4,<2.0.0)
Requires-Dist: requests (>=2.32.5,<3.0.0)
Requires-Dist: scikit-image (>=0.25.2,<0.26.0)
Requires-Dist: scipy (>=1.15.3,<2.0.0)
Requires-Dist: types-Pillow (>=10.2.0.20240822,<11.0.0.0)
Requires-Dist: typing_extensions (>=4.14.1,<5.0.0)
Project-URL: Documentation, https://github.com/liebharc/homr
